ngus/__init__.py
ngus/__main__.py
ngus-1.0.dist-info/COPYING
ngus-1.0.dist-info/LICENSE
ngus-1.0.dist-info/METADATA
ngus-1.0.dist-info/WHEEL
ngus-1.0.dist-info/entry_points.txt
ngus-1.0.dist-info/top_level.txt
ngus-1.0.dist-info/RECORD
