Metadata-Version: 2.1
Name: ngus
Version: 1.0
Summary: A simple HTTP server for handleing file uploads
Home-page: https://github.com/blackm0re/ngus
Author: Simeon Simeonov
Author-email: sgs@pichove.org
License: UNKNOWN
Project-URL: Bug Reports, https://github.com/blackm0re/ngus/issues
Project-URL: Source, https://github.com/blackm0re/ngus
Keywords: upload http httpd
Platform: UNKNOWN
Classifier: Development Status :: 5 - Production/Stable
Classifier: Intended Audience :: End Users/Desktop
Classifier: License :: OSI Approved :: GNU General Public License v3 or later (GPLv3+)
Classifier: Programming Language :: Python :: 3 :: Only
Classifier: Programming Language :: Python :: 3.6
Classifier: Programming Language :: Python :: 3.7
Classifier: Programming Language :: Python :: 3.8
Classifier: Programming Language :: Python :: 3.9
Classifier: Programming Language :: Python :: 3.10
Classifier: Programming Language :: Python :: Implementation
Classifier: Operating System :: OS Independent
Classifier: Topic :: Internet :: WWW/HTTP :: HTTP Servers
Requires-Python: >=3.6
License-File: LICENSE
License-File: COPYING
